scope/__init__.py
scope/_version.py
scope/broadening.py
scope/calc_quantities.py
scope/ccf.py
scope/constants.py
scope/download_data.bash
scope/emcee_fit_hires.py
scope/grid.py
scope/input.txt
scope/input_output.py
scope/noise.py
scope/rm_effect.py
scope/run_simulation.py
scope/tellurics.py
scope/utils.py
scope/tests/__init__.py
scope/tests/conftest.py
scope/tests/test_broadening.py
scope/tests/test_ccf.py
scope/tests/test_constants.py
scope/tests/test_emcee_fit_hires.py
scope/tests/test_grid.py
scope/tests/test_io.py
scope/tests/test_rm.py
scope/tests/test_run_simulation.py
scope/tests/test_utils.py
scope_astr-0.4.4b0.dist-info/LICENSE
scope_astr-0.4.4b0.dist-info/METADATA
scope_astr-0.4.4b0.dist-info/WHEEL
scope_astr-0.4.4b0.dist-info/top_level.txt
scope_astr-0.4.4b0.dist-info/RECORD
