Metadata-Version: 2.1
Name: scope-astr
Version: 0.4.4b0
Summary: Simulating high-resolution spectroscopy of exoplanet atmospheres.
Author: Megan Bedell, Eliza M.-R. Kempton, Peter Smith, Jacob L. Bean, Lily L. Zhao, Jorge A. Sanchez, Michael R. Line
Author-email: Arjun Savel <asavel@umd.edu>
License: MIT
Project-URL: Homepage, https://github.com/arjunsavel/scope
Project-URL: Issues, https://github.com/arjunsavel/scope/issues
Project-URL: Documentation, https://scope-astr.readthedocs.io/en/latest/
Keywords: astronomy
Classifier: Development Status :: 4 - Beta
Classifier: Intended Audience :: Developers
Classifier: Intended Audience :: Science/Research
Classifier: Natural Language :: English
Classifier: License :: OSI Approved :: MIT License
Classifier: Programming Language :: Python
Classifier: Programming Language :: Python :: 3.10
Classifier: Programming Language :: Python :: 3.11
Classifier: Topic :: Scientific/Engineering :: Astronomy
Requires-Python: >=3.10
License-File: LICENSE
Requires-Dist: numpy
Requires-Dist: astropy >5.1
Requires-Dist: scipy
Requires-Dist: jax
Requires-Dist: exoplanet
Requires-Dist: tqdm
Requires-Dist: emcee
Requires-Dist: numba
Requires-Dist: scikit-learn >=1.3.0
Requires-Dist: matplotlib
Requires-Dist: pandas
Requires-Dist: exoplanet-core
Requires-Dist: pymc >=4
Requires-Dist: schwimmbad
Provides-Extra: docs
Requires-Dist: nbsphinx ; extra == 'docs'
Requires-Dist: nbconvert ; extra == 'docs'
Requires-Dist: pygments >=2.4.2 ; extra == 'docs'
Requires-Dist: Jinja2 ==3.1.3 ; extra == 'docs'
Requires-Dist: sphinx-book-theme ; extra == 'docs'
Requires-Dist: markupsafe ==2.0.1 ; extra == 'docs'
Requires-Dist: mock ; extra == 'docs'
